definet/__init__.py
definet/__main__.py
definet/rgb.py
definet-0.1.4.dist-info/licenses/LICENSE
definet-0.1.4.dist-info/METADATA
definet-0.1.4.dist-info/WHEEL
definet-0.1.4.dist-info/entry_points.txt
definet-0.1.4.dist-info/top_level.txt
definet-0.1.4.dist-info/RECORD
