Metadata-Version: 2.4
Name: definet
Version: 0.1.4
Summary: a tool that will give you the definition of any word you like.
Author-email: sigmacodeslol <tcrrxzz@gmail.com>
License-Expression: MIT
Project-URL: Repository, https://github.com/sigmacodeslol/definet.git
Classifier: Development Status :: 2 - Pre-Alpha
Classifier: Programming Language :: Python :: 3.12
Classifier: Programming Language :: Python :: 3.13
Requires-Python: >=3.12
License-File: LICENSE
Requires-Dist: pyenchant
Requires-Dist: requests
Dynamic: license-file
